README.txt
setup.py
dummycache/__init__.py
dummycache/cache.py
dummycache/datetimestub.py
dummycache/test_cache.py
dummycache.egg-info/PKG-INFO
dummycache.egg-info/SOURCES.txt
dummycache.egg-info/dependency_links.txt
dummycache.egg-info/top_level.txt
setup/devenv.txt