Metadata-Version: 1.0
Name: dummycache
Version: 0.0.2
Summary: A dummy in-memory cache for development and testing. (Not recommended for production use.)
Home-page: http://code.google.com/p/dummycache/
Author: Vichaya Sirisanthana
Author-email: vsirisanthana@gmail.com
License: GPL-3.0
Download-URL: http://pypi.python.org/pypi/dummycache
Keywords: cache python
Platform: UNKNOWN
Classifier: Development Status :: 3 - Alpha
Classifier: Intended Audience :: Developers
Classifier: Programming Language :: Python
Classifier: Topic :: Software Development :: Libraries :: Python Modules
Classifier: License :: OSI Approved :: GNU General Public License (GPL)
